[{
  "id": 43981,
  "id": 43981,
  "id": 43981,
  "name": "Paloma",
  "surname": "Southwell",
  "email": "psouthwell0@phoca.cz",
  "phone": "+33 132 739 5721",
  "customerNo": 1,
  "postalCode": "91914 CEDEX 9",
  "shipAddress": "58 Sauthoff Pass",
  "billAddress": "1 Vernon Drive",
  "insDate": "2022-06-22"
}, {
  "id": 42025,
  "name": "Kerr",
  "surname": "Plastow",
  "email": "kplastow1@cafepress.com",
  "phone": "+7 367 455 4683",
  "customerNo": 2,
  "postalCode": "440999",
  "shipAddress": "2626 Sycamore Pass",
  "billAddress": "98 Briar Crest Point",
  "insDate": "2023-02-25"
}, {
  "id": 62271,
  "name": "Cilasun",
  "surname": "Fish",
  "email": "afish2@moonfruit.com",
  "phone": "+86 304 853 6380",
  "customerNo": 3,
  "postalCode": null,
  "shipAddress": "5577 Dunning Drive",
  "billAddress": "569 Gateway Road",
  "insDate": "2022-12-05"
}]